assrs-0.1.2.dist-info/METADATA
assrs-0.1.2.dist-info/WHEEL
assrs/__init__.py
assrs/__init__.pyi
assrs/py.typed
assrs/assrs.cpython-38-s390x-linux-gnu.so
assrs-0.1.2.dist-info/RECORD
